odoo8_addon_account_reset_chart-8.0.1.0.0.99.dev19-py3.8-nspkg.pth
odoo_addons/account_reset_chart/README.rst
odoo_addons/account_reset_chart/__init__.py
odoo_addons/account_reset_chart/__openerp__.py
odoo_addons/account_reset_chart/i18n/account_reset_chart.pot
odoo_addons/account_reset_chart/i18n/am.po
odoo_addons/account_reset_chart/i18n/ar.po
odoo_addons/account_reset_chart/i18n/ca.po
odoo_addons/account_reset_chart/i18n/da.po
odoo_addons/account_reset_chart/i18n/de.po
odoo_addons/account_reset_chart/i18n/el_GR.po
odoo_addons/account_reset_chart/i18n/es.po
odoo_addons/account_reset_chart/i18n/es_ES.po
odoo_addons/account_reset_chart/i18n/es_MX.po
odoo_addons/account_reset_chart/i18n/eu.po
odoo_addons/account_reset_chart/i18n/fi.po
odoo_addons/account_reset_chart/i18n/fr.po
odoo_addons/account_reset_chart/i18n/fr_CA.po
odoo_addons/account_reset_chart/i18n/fr_FR.po
odoo_addons/account_reset_chart/i18n/hr.po
odoo_addons/account_reset_chart/i18n/hr_HR.po
odoo_addons/account_reset_chart/i18n/it.po
odoo_addons/account_reset_chart/i18n/nb.po
odoo_addons/account_reset_chart/i18n/nb_NO.po
odoo_addons/account_reset_chart/i18n/nl.po
odoo_addons/account_reset_chart/i18n/nl_BE.po
odoo_addons/account_reset_chart/i18n/nl_NL.po
odoo_addons/account_reset_chart/i18n/pt_BR.po
odoo_addons/account_reset_chart/i18n/ro.po
odoo_addons/account_reset_chart/i18n/sk.po
odoo_addons/account_reset_chart/i18n/sl.po
odoo_addons/account_reset_chart/i18n/tr.po
odoo_addons/account_reset_chart/i18n/zh_CN.po
odoo_addons/account_reset_chart/models/__init__.py
odoo_addons/account_reset_chart/models/res_company.py
odoo_addons/account_reset_chart/static/description/icon.png
odoo8_addon_account_reset_chart-8.0.1.0.0.99.dev19.dist-info/METADATA
odoo8_addon_account_reset_chart-8.0.1.0.0.99.dev19.dist-info/WHEEL
odoo8_addon_account_reset_chart-8.0.1.0.0.99.dev19.dist-info/namespace_packages.txt
odoo8_addon_account_reset_chart-8.0.1.0.0.99.dev19.dist-info/top_level.txt
odoo8_addon_account_reset_chart-8.0.1.0.0.99.dev19.dist-info/RECORD
